{
    "description": "Zen mode for YouTube",
    "manifest_version": 2,
    "name": "ZenTube",
    "version": "1.0.17",
    "author": "surajsharma",
    "homepage_url": "https://evenzero.in",
    "icons": {
        "144": "icons/favicon4_144.png"
    },

    "background": {
        "scripts": ["background.js"]
    },

    "content_scripts": [
        {
            "matches": ["*://*.youtube.com/*"],
            "js": ["browser-polyfill.js", "contentscript.js"],
            "run_at": "document_start"
        }
    ],

    "browser_action": {
        "default_icon": "icons/favicon4_144.png",
        "default_title": "Less Addictive Youtube",
        "default_popup": "options/options.html"
    },

    "permissions": ["storage", "tabs", "scripting"]
}
